{
  "url": "https://www.city.suita.osaka.jp/sangyo/1018028/1018029/1018030/1011571.html",
  "title": "知的財産権取得事業補助金",
  "municipality_id": "suita",
  "source_type": "html",
  "text": "ここから本文です。\n\n[PDFより]\n吹田市知的財産権取得事業補助金募集要項\n１ 概要\n企業価値及び資質の向上を図ることを目的として、知的財産権を取得した中小企業者に対し\nて経費の一部を補助します。\n２ 補助対象者\n⑴ 市内に主たる事業所を有する中小企業者\n⑵ 市町村民税の滞納（不申告を含む。）をしていない者\n⑶ 風俗営業等の規制及び業務の適正化等に関する法律（昭和23年法律第122号）第２条に規定\nする風俗営業、性風俗関連特殊営業、特定遊興飲食店営業又は接客業務受託営業に該当する事\n業を営んでいない者\n３ 補助対象事業\n特許権又は実用新案権を取得する事業\n４ 補助対象経費\n⑴ 特許権の取得の場合 ⑵ 実用新案権の取得の場合\nア 出願料 ア 出願料\nイ 電子化手数料 イ 電子化手数料\nウ 審査請求料 ウ 当初３年分の登録料\nエ 当初３年分の特許料 エ 出願に係る弁理士費用\nオ 出願に係る弁理士費用\n５ 補助金の額等\n⑴ 補助金の額\nア 特許権の場合：上限20万円（補助率２分の１）\nイ 実用新案権の場合：上限10万円（補助率２分の１）\n⑵ 補助金交付回数\n１年度、１事業者につき1回限り\n６ 申請方法\n⑴ 提出書類\nア 吹田市知的財産権取得事業補助金交付申請書【様式第１号】\nイ 企業概要書【様式第２号】\nウ 共同出願者の概要【様式第３号】 ※共同出願を行った場合のみ\nエ 知的財産権の概要【様式第４号】\nオ 法人の場合、履歴事項全部証明書の写し\nカ 個人の場合、直近の確定申告書及び個人事業の開業届出書の写し\nキ 直近の市町村民税の納税又は非課税を証する書類の写し\nク 知的財産権の取得を証する書類\nケ 知的財産権出願時に提出した図面及び要約書の写し\nコ 補助対象経費の支払を証する書類\n※ア～エは吹田市のホームページから様式をダウンロードして使用してください。\n⑵ 提出方法\n⑴の書類を地域経済振興室へＥメール又は郵送（レターパックライト)で提出してください。\n※Ｅメールでの提出を御希望の場合は、必ず事前に御連絡ください。また、連絡後に\nデータを提出する場合、ファイル名を⑴の書類名にしてください。\n⑶ 申請期限\n知的財産権を取得した日の翌日から起算して１年以内\n７ 補助金交付手続きの流れ\n１ 知的財産権の取得 （事業者）\n２ 交付申請書類の提出 （事業者→市）\n３ 交付決定通知書の送付 （市→事業者）\n４ 交付請求書類の提出 （事業者→市）\n５ 補給金の交付 （市→事業者）\n８ 申込み・問合せ先\n吹田市都市魅力部地域経済振興室 企業振興担当\n〒564-8550 吹田市泉町１－３－40\n電話番号 06-6170-7217\nメールアドレス sanro_s@city.suita.osaka.jp\n\n[PDFより]\n吹田市知的財産権取得事業補助金交付要領\n制定 令和４年４月19日決裁\n最終改正 令和６年８月30日決裁\n１ 趣旨\n知的財産権を取得した中小企業者に対し、予算の範囲内において、吹田市知的財産権\n取得事業補助金（以下「補助金」という。）を交付する。\n２ 定義\n⑴ 知的財産権 特許権及び実用新案権をいう。\n⑵ 中小企業者 中小企業基本法（昭和38年法律第154号）第２条第１項に定める中小\n企業者である会社及び個人。ただし、次のいずれかに該当する中小企業者は除く。\nア 発行済株式の総数又は出資金額の総額の２分の１以上を同一の大企業（中小企業\n者以外のものであって、事業を営む者をいう。以下同じ。）が所有していること。\nイ 発行済株式の総数又は出資金額の総額の３分の２以上を大企業が所有しているこ\nウ 大企業の役員又は職員を兼ねている者が、役員総数の２分の１以上を占めている\nこと。\n３ 補助対象者\n補助の対象となる者は、次のいずれにも該当する者とする。\nア 市内に主たる事業所を有する中小企業者であること。\nイ 市町村民税の滞納（不申告を含む。）をしていないこと。\nウ 風俗営業等の規制及び業務の適正化等に関する法律（昭和23年法律第122号）第\n２条第１項に規定する風俗営業、同条第５項に規定する性風俗関連特殊営業、同条第\n11 項に規定する特定遊興飲食店営業又は同条第 13 項に規定する接客業務受託営業\nに該当する事業を営んでいないこと。\n４ 補助対象事業\n⑴ 補助の対象となる事業は、次のいずれかの事業とする。\nア 特許権を取得する事業\nイ 実用新案権を取得する事業\n⑵ ⑴の規定に関わらず、国、大阪府その他の公共団体又は公共的団体から補助金等を受\nけている事業及び受ける見込みのある事業は、補助対象としない。\n５ 補助対象経費\n補助の対象となる経費は、補助対象事業の実施に要する経費のうち、次の経費とする。\n1 / 4\nア 特許権の取得の場合\n(ｱ) 出願料\n(ｲ) 電子化手数料\n(ｳ) 審査請求料\n(ｴ) 当初３年分の特許料\n(ｵ) 出願に係る弁理士費用\nイ 実用新案権の取得の場合\n(ｱ) 出願料\n(ｲ) 電子化手数料\n(ｳ) 当初３年分の登録料\n(ｴ) 出願に係る弁理士費用\n６ 補助金の額等\n⑴ 補助金の額は、補助対象経費の総額に２分の１を乗じた額とする。ただし、1,000円\n未満の端数があるときは、これを切り捨てる。\n⑵ ４⑴アの場合は、200,000円を上限とする。\n⑶ ４⑴イの場合は、100,000円を上限とする。\n⑷ 補助金の交付は、１の年度に１回限りとする。\n７ 手続の概要\n⑴ 手続の流れ\nア 補助金の交付申請\nイ 補助金の交付決定\nウ 補助金の交付請求\nエ 補助金の交付\n⑵ 交付申請の日及び交付決定の日は、同一年度内でなければならない。\n８ 補助金の交付申請\n⑴ 申請の時期 知的財産権を取得した日の翌日から起算して１年以内\n⑵ 提出書類\nア 補助金交付申請書（様式第１号）\nイ 企業概要書（様式第２号）\nウ 共同出願者の概要（様式第３号）（共同出願を行った場合のみ）\nエ 知的財産権の概要（様式第４号）\nオ 法人の場合、履歴事項全部証明書の写し\nカ 個人の場合、直近の確定申告書及び個人事業の開業届出書の写し\n2 / 4\nキ 直近の市町村民税の納付又は非課税を証する書類\nク 知的財産権の取得を証する書類\nケ 知的財産権出願時に提出した図面及び要約書の写し\nコ 補助対象経費の支払を証する書類\n９ 補助金の交付決定\n⑴ 補助金交付申請書等の内容を審査し、適当と認めるときは、補助金交付決定通知書\n（様式第５号）により申請者に通知する。\n⑵ 交付決定の通知の際に、補助金交付請求書等の提出期限を通知する。\n10 補助金の交付請求\n⑴ 請求の時期 指定された期限まで\n⑵ 提出書類\nア 補助金交付請求書（様式第６号）\nイ 補助金の振込先口座の通帳の写し等\n11 補助金の交付\n補助金交付請求書等の内容を審査し、適当と認めるときは、補助金を交付する。\n12 帳簿の整備等\n補助金の交付を受けた者は、次の書類を、補助金の交付後10年間保管しなければな\nらない。\nア 補助対象事業に係る支出を明らかにした帳簿\nイ 当該支出についての証拠書類\n13 調査\n⑴ 調査の必要があると認めるときは、補助金の交付決定を受けた者に対し、補助対象事\n業の実施状況について、帳簿又は証拠書類等の提出を求め、調査若しくは質問をするこ\nとができる。\n⑵ 補助金の交付決定を受けた者は、正当な理由がない限り、⑴の調査を拒んではならな\n14 補助金の交付決定の取消し等\n⑴ 補助金の交付決定を受けた者が次のいずれかに該当するときは、補助金の交付決定\nの全部又は一部を取り消すことができる。\nア 偽りその他の不正な手段により補助金の交付を受けたとき又は受けようとしたと\n3 / 4\nイ 12又は13⑵に違反したとき。\n⑵ 補助金の交付決定を取り消したときは、取消しの理由を記載した補助金交付決定取\n消通知書により、その者に通知する。また、取消しに係る部分に関し既に補助金を交付\nしているときは、併せて、返還すべき額及び返還期限を通知する。\n⑶ 既に交付を受けた補助金の交付決定の全部又は一部を取り消された者は、指定され\nた期限までに、その返還をしなければならない。\n15 施行期日\nこの要領は、令和６年９月１日から施行する。\n4 / 4\n\n[PDFより]\n様式第１号\n吹田市知的財産権取得事業補助金交付申請書\n年 月 日\n吹田市長 宛\n申請者 事業所所在地\nフリガナ\n事業者名（屋号）\n代表者役職\nフリガナ\n代表者氏名\n電話番号\n担当者名\n次のとおり吹田市知的財産権取得事業補助金の交付を申請します。また、吹田市\n知的財産権取得事業補助金交付要領に定める対象要件を全て満たしていることを誓\n約します。\n１ 実 施 事 業 特許権の取得 ・ 実用新案権の取得\n２ 交付申請額（千円未満切捨） 円\n３ 補助対象経費（税込） 円\n４ 知的財産権取得日 年 月 日\n※ 添付書類\n⑴ 企業概要書（様式第２号）\n⑵ 共同出願者の概要（様式第３号）（共同出願を行った場合のみ）\n⑶ 知的財産権の概要（様式第４号）\n⑷ 法人の場合、履歴事項全部証明書の写し\n⑸ 個人の場合、直近の確定申告書及び個人事業の開業届出書の写し\n⑹ 直近の市町村民税の納付又は非課税を証する書類\n⑺ 知的財産権の取得を証する書類\n⑻ 知的財産権出願時に提出した図面及び要約書の写し\n⑼ 補助対象経費の支払を証する書類",
  "content_hash": "62ea1bdc93a86e28586cc36a1bfe4dac6e487bedee73d56aa5dc0f683cc1473a",
  "scraped_at": "2026-04-28T14:55:23.212706+00:00"
}