{
  "url": "https://www.pref.osaka.lg.jp/o180160/shigaku/shigakumushouka/syougaku_kyuuhu.html",
  "title": "大阪府私立高等学校等奨学のための給付金について",
  "municipality_id": "osaka_pref",
  "source_type": "html",
  "text": "ここから本文です。\n\n[PDFより]\n【大阪府認可の高等学校等用・通常制度】\n【重要】\nこのお知らせは、必ず保護者に渡してください。 （令和７年度）\n私立高等学校等奨学のための給付金受給申請手続きについて\n制度概要\n全ての意志ある生徒が安心して教育を受けられるよう、府内に在住する低所得者世帯の保護者等に対し、授業料以外\nの教育費の経済的負担を軽減するために、奨学のための給付金を支給します。（返済の必要はありません。）\n要 件\n７ ７ １\n令和 年 月 日時点において、次の①～⑤の要件をすべて満たしている必要があります。\n① 保護者等全員の令和７年度の市町村民税及び道府県民税の所得割（以下「所得割」という。）が非課税、\nもしくは生活保護（生業扶助）受給世帯であること\n② 保護者等全員が、大阪府内に在住していること（※）\n③ 生徒が、高等学校等就学支援金の支給を受ける資格を有する者、または大阪府私立高等学校等学び直し支援金の\n補助対象となる者であること\n④ 生徒が、高等学校等就学支援金の支給対象校に在学し、休学していないこと（令和８年３月１日までに復学\nした場合は給付対象となりますので、復学日までに学校事務室にお問い合わせください。）\n⑤ 生徒が、平成26年４月１日以降に、高等学校等の第１学年に入学していること（平成27年４月１日以降に\n第２学年に、平成28年４月１日以降に第２・３学年に編転入学している生徒を含みます。）\n※ 保護者等のいずれか一方が他の都道府県に在住している場合は、生活の本拠が大阪府内にある世帯で、\nかつ、他の都道府県に対し奨学のための給付金を申請しない場合に限り、申請できます。\n給付金額\n申請先\n在学する高等学校等\n申請期限 申請書類等は、必ず学校が定める期限までに学校事務室に提出してください。\n学校が定める期限\n5 2\n, 6 0\n, 1\n0 円\n申請に必要な書類\n支給を受けようとする保護者等は、下記の書類を学校の定める期日までに提出してください。\n下記の区分については、表面の【給付金額】をご参照ください。\n※保護者等全員の課税額を証明する書類が提出できない場合（例：海外単身赴任の場合等）については、給付金を受け取\nることができません。\n給付金申請及び支給の流れ\n① 学校がリーフレット及び受給申請書等を保護者等に配布（配布方法は在学する学校にお問合せください）\n② 申請者が受給申請書等を学校に提出（書類の不足等がある場合は、学校から連絡をします）\n③ 学校が受給申請書等を府に送付\n④ 府が受給資格の確認（書類の不備等がある場合は、府から申請者に確認の連絡をします）（9月以降随時）\n⑤ 府が受給資格認定及び支給金額の決定 （12月以降予定）\n⑥ 府が学校に認定結果等の通知を送付並びに給付金を交付（学校が代理受領） （12月以降予定）\n⑦ 学校が保護者等に通知を配付及び給付金を口座へ振込 （1月以降予定）\n※ 生徒が在学する高等学校等の設置者に、給付金の受給申請に関する事務手続き及び給付金の代理受領を委任していただきます。\n給付金額全額が学校から保護者等の口座に振り込まれます。ただし、未納・未収金がある場合は、給付金を充当して相殺し、\n残金がある場合は残金が学校から保護者等の口座に振り込まれます。\n※ 給付金が振り込まれるまで、授業料以外の学校納付金の納付が困難で、一時的な納付猶予を希望する場合は、在学する学校に\nご相談ください。\n制度に関する問合せ先\n●府民お問合せセンター ピピっとライン 電話：06－6910－8001 ＦＡＸ：06－6910－8005\n●教育庁 私学課 奨学のための給付金担当 電話：06－6941－0351（代）ＦＡＸ：06－6210－9276\n〒540-8570 大阪市中央区大手前３－１－４３ 大阪府庁新別館南館９階\n●大阪府ホームページ 「大阪府私立高等学校等奨学のための給付金について」 携帯、スマートフォンから→\nhttps://www.pref.osaka.lg.jp/shigaku/shigakumushouka/syougaku_kyuuhu.html\n区 分\n受 給\nあ っ\n令 和\n扶 助\n下 記\n● 市\n● 市\n● 市\n配 偶\n下 記\n● 住\n● 令\n提 出 書 類\n奨 学 の た め の 給 付 金 受 給 申 請 書 （ 様\nの 提 出 後 に 、 申 請 者 の 変 更 （ 例 ： 離 婚 ・ 死 別 等 に よ る 親 権\n、 学 校 か ら 申 請 事 項 変 更 届 （ 様 式 第 ２ 号 ） の 用 紙 を も ら い 、\n生 活 保 護 受 給 証 明 書 の 原 本\n７ １\n月 日 以 降 に 発 行 さ れ た も の\n（ 生 業 扶 助 ） ・ 世 帯 全 員 の 氏 名 ・ 生 年 月 日 ・ 受 給 期 間 が 記\n保 護 者 等 全 員 の 課 税 証 明 書 等\nの い ず れ か （ 令 和 ７ 年 度 の も の ） を ご 提 出 く だ さ い 。\n） 民 税 ・ 道 府 県 民 税 課 税 証 明 書 ま た は 非 課 税 証 明 書 の 原 本\n） 民 税 ・ 道 府 県 民 税 非 課 税 通 知 書 の 写 し\n） 民 税 ・ 道 府 県 民 税 の 特 別 徴 収 税 額 の 決 定 通 知 書 の 写 し\nを 受 け て い る 場 合 で あ っ て も 、 控 除 対 象 配 偶 者 の 課 税 証 明 書\n住 民 票\nれ か に 該 当 す る 場 合 に 提 出 し て く だ さ い 。\n課 税 額 等 を 証 明 す る 書 類 の 発 行 者 が 大 阪 府 以 外 の 市 町 村 で\n７ 月 １ 日 時 点 で 大 阪 府 内 に 在 住 し て い る が 、 令 和 ７ 年 １ 月\nも の\n、 申\nし て\n必 要\nは 他\nく だ\nて い\n\n[PDFより]\n【大阪府認可校以外の高等学校等用・通常制度】\n【重要】\nこのお知らせは、必ず保護者に渡してください。 （令和７年度）\n私立高等学校等奨学のための給付金受給申請手続きについて\n制度概要\n全ての意志ある生徒が安心して教育を受けられるよう、府内に在住する低所得者世帯の保護者等に対し、授業料以外\nの教育費の経済的負担を軽減するために、奨学のための給付金を支給します。（返済の必要はありません。）\n要 件\n７ ７ １\n令和 年 月 日時点において、次の①～⑤の要件をすべて満たしている必要があります。\n① 保護者等全員の令和７年度の市町村民税及び道府県民税の所得割（以下「所得割」という。）が非課税、\nもしくは生活保護（生業扶助）受給世帯であること\n② 保護者等全員が、大阪府内に在住していること（※）\n③ 生徒が、高等学校等就学支援金の支給を受ける資格を有する者、または大阪府私立高等学校等学び直し支援金の\n補助対象となる者であること\n④ 生徒が、高等学校等就学支援金の支給対象校に在学し、休学していないこと（令和８年３月１日までに復学\nした場合は給付対象となりますので、復学日までに学校事務室にお問い合わせください。）\n⑤ 生徒が、平成26年４月１日以降に、高等学校等の第１学年に入学していること（平成27年４月１日以降に\n第２学年に、平成28年４月１日以降に第２・３学年に編転入学している生徒を含みます。）\n※ 保護者等のいずれか一方が他の都道府県に在住している場合は、生活の本拠が大阪府内にある世帯で、かつ、\n他の都道府県に対し奨学のための給付金を申請しない場合に限り、申請できます。\n給付金額\n申請書類等は、必ず期限内に提出してください。\n申請期限\n令和７年10月31日（金曜日）【消印有効】\n※郵便の消印日付が令和7年1１月1日以降の場合、給付金を受け取ることができませんので、ご注意ください。\n※10月31日に発送する場合は、必ず郵便局で10月31日の消印を受けてください。\n給付金の支給の流れ\n受給資格の確認\n受給申請書を 受給資格認定及び 保護者等の\n（書類の不備等がある場合は、\n府に郵送 支給金額の決定・通知 口座へ振込\n府から確認の連絡をします）\n（９/１～10/31の消印有効） （９月～12月） （令和８年1月頃） （令和８年１月頃の予定）\n5 2\n, 6 0\n, 1\n0 円\n申請に必要な書類\n支給を受けようとする保護者等は、下記の書類を大阪府の定める期日までに提出してください。\n下記の区分については、表面の【給付金額】をご参照ください。\n※保護者等全員の課税額を証明する書類が提出できない場合（例：海外単身赴任の場合等）については、給付金を受け取\nることができません。\n送付先\n〒540-8570 大阪市中央区大手前３-１-４３ 大阪府庁新別館南館９階\n大阪府教育庁 私学課 奨学のための給付金担当 宛\n※ 普通郵便の場合、追跡確認はできません。また、電話問合せによる到達確認にも対応できません。\n※ 郵便事故等が心配な方は、特定記録や簡易書留による郵便をご利用ください。\n（郵便局HP等において到達までの追跡が可能です。）\n問合せ先\n●府民お問合せセンター ピピっとライン 電話：06－6910－8001 ＦＡＸ：06－6910－8005\n●教育庁 私学課 奨学のための給付金担当 電話：06－6941－0351（代）ＦＡＸ：06－6210－9276\n〒540-8570 大阪市中央区大手前３－１－４３ 大阪府庁新別館南館９階\n●大阪府ホームページ 「大阪府私立高等学校等奨学のための給付金について」\nhttps://www.pref.osaka.lg.jp/shigaku/shigakumushouka/syougaku_kyuuhu.html\n携帯、スマートフォンから→\n区 分\n申 請\nた 場\nの 種\nの 書\n（ 町\n（ 町\n（ 町\n者 控\n申 請\n機 関\nの い\nの 提\n、 大\n７ 月\n（ 生\nの い\n） 民\n） 民\n） 民\nを 受\nの ３\n、 支\nれ か\nの 課\n年 ７\n提 出 書 類\n学 の た め の 給 付 金 受 給 申 請 書 （ 様\n出 後 に 、 申 請 者 の 変 更 （ 例 ： 離 婚 ・ 死 別 等 に よ る 親 権\n阪 府 ホ ー ム ペ ー ジ か ら 申 請 事 項 変 更 届 （ 様 式 第 ２ 号 ） の\n活 保 護 受 給 証 明 書 の 原 本\n１ 日 以 降 に 発 行 さ れ た も の\n業 扶 助 ） ・ 世 帯 全 員 の 氏 名 ・ 生 年 月 日 ・ 受 給 期 間 が 記\n護 者 等 全 員 の 課 税 証 明 書 等\nず れ か （ 令 和 ７ 年 度 の も の ） を ご 提 出 く だ さ い 。\n税 ・ 道 府 県 民 税 課 税 証 明 書 ま た は 非 課 税 証 明 書 の 原 本\n税 ・ 道 府 県 民 税 非 課 税 通 知 書 の 写 し\n税 ・ 道 府 県 民 税 の 特 別 徴 収 税 額 の 決 定 通 知 書 の 写 し\nけ て い る 場 合 で あ っ て も 、 控 除 対 象 配 偶 者 の 課 税 証 明 書\n徒 本 人 の 令 和 ７ 年 ７ 月 １ 日 時 点 の\nペ ー ジ 下 段 に 、 学 校 長 の 証 明 を 受 け る 場 合 、 在 学 証 明 書\n付 金 振 込 先 口 座 の 通 帳 等 の 写 し\n店 名 、 口 座 番 号 、 口 座 名 義 人 が 分 か る ペ ー ジ の 写 し （ ネ\n民 票\nに 該 当 す る 場 合 に 提 出 し て く だ さ い 。\n税 額 等 を 証 明 す る 書 類 の 発 行 者 が 大 阪 府 以 外 の 市 町 村\n月 １ 日 時 点 で 大 阪 府 内 に 在 住 し て い る が 、 令 和 ７ 年 １ 月\n式 第 １ 号 の\n者 の 変 更 ） 、 申 請\n用 紙 を 印 刷 し 、 大\n載 さ れ た も の\n等 の 提 出 が 必 要 で\n在 学 を 証 明\nは 省 略 で き ま す 。\nッ ト バ ン キ ン グ 可 ）\nで あ る 場 合\n１ 日 時 点 で は 他\nて く\nく だ\nい 。\nし て\n\n[PDFより]\n令和７年度 大阪府所轄私立各種学校一覧\n学校の主たる所在地\n学校名 学校電話番号\n郵便番号 住所\n2404 東大阪准看護学院 577-0843 東大阪市荒川2-32-43 06-6720-0307\n2501 関西調理師学校 535-0002 大阪市旭区大宮4-7-12 06-6951-8032\n2941 関西学院大阪インターナショナルスクール 562-0032 箕面市小野原西4-4-16 072-727-5050\n2942 コリア国際学園 567-0057 茨木市豊川2-13-35 072-643-4200",
  "content_hash": "0fbc0ccda2ee30f77a6758648080f83f2ba345198941731c653e01bed7d3b2fb",
  "scraped_at": "2026-04-29T05:16:33.887808+00:00"
}