{
  "url": "https://www.city.osaka.lg.jp/toshiseibi/page/0000648452.html",
  "title": "市営住宅用地の使用事業者募集の結果について（都市整備局　建設課実施分）",
  "municipality_id": "osaka",
  "source_type": "html",
  "text": "市営住宅用地の使用事業者募集の結果について（都市整備局　建設課実施分）\n2026年3月11日\nページ番号：648452\n先着順申込受付結果\n令和8年3月9日から実施分\n市営住宅用地の使用事業者募集結果\n物件番号\n所在地\n（住居表示）\n使用許可面積\n（平方メートル）\n使用料\n（月額）\n決定使用者名\nD-3\n大阪市住吉区浅香1丁目82番1内外\n（浅香1丁目1番街区）\n973.62\n233,668円\n株式会社光開発\n価格提案審査結果\n令和8年2月26日実施分\n市営住宅用地の使用事業者募集結果\n物件番号\n所在地\n（住居表示）\n使用許可面積\n（平方メートル）\n最低使用料\n（予定価格）\n（月額・税抜）\n申込者数\n価格提案\n数\n決定使用料\n（月額）\n決定使用者名\nD-1\n大阪市西成区南開2丁目1番4内\n（南開2丁目6番街区）\n281.33\n70,100円\n3\n3\n274,000円\n日本マルコニー株式会社\nD-2\n大阪市大正区泉尾2丁目101番7\n（泉尾2丁目1番街区）\n248.24\n79,436円\n3\n3\n260,000円\n株式会社イワセ\nD-3\n大阪市住吉区浅香1丁目82番1内外\n（浅香1丁目1番街区）\n973.62\n233,668円\n0\n0\nなし\nなし\nD-4\n大阪市浪速区日本橋5丁目32番2内外\n（日本橋5丁目20番街区）\n283.05\n234,931円\n2\n2\n330,000円\nタイムズ24株式会社\n経過調書\n経過調書(PDF形式, 89.30KB)\nCC（クリエイティブコモンズ）ライセンス\nにおける\nCC-BY4.0\nで提供いたします。\nオープンデータを探す\n大阪市オープンデータポータルサイト\n令和7年2月28日実施分\n市営住宅用地の使用事業者募集結果\n所在地\n（住居表示）\n使用許可面積\n（平方メートル）\n最低使用料\n（予定価格）\n（月額・税抜）\n申込者数\n価格提案\n数\n決定使用料\n（月額）\n決定使用者名\n住之江区中加賀屋1丁目14番内\n（1丁目10番街区）\n521.25\n166,800円\n4\n4\n462,000円\n三井不動産リアルティ株式会社\n住吉区南住吉4丁目46番内\n（4丁目14番街区）\n633.67\n202,774円\n0\n0\nなし\nなし\n経過調書\n経過調書(PDF形式, 132.84KB)\nCC（クリエイティブコモンズ）ライセンス\nにおける\nCC-BY4.0\nで提供いたします。\nオープンデータを探す\n大阪市オープンデータポータルサイト\nAdobe Acrobat Reader DCのダウンロード（無償）\nPDFファイルを閲覧できない場合には、Adobe 社のサイトから Adobe Acrobat Reader DC をダウンロード（無償）してください。\n探している情報が見つからない\n情報が見つからないときは\nこのページの作成者・問合せ先\n都市整備局 住宅部 建設課 団地再生グループ\n電話: 06-6208-9273 ファックス: 06-6202-7063\n住所: 〒530-8201　大阪市北区中之島1丁目3番20号（大阪市役所1階）",
  "content_hash": "569e2eb7e3f82ba9dcdc59b5387d0531aa59c379e46022f9cf5f086f7982ef48",
  "scraped_at": "2026-05-03T14:06:27.806242+00:00"
}